{"Q":{"type":"physical","area":true,"min":["(45 + 1.4 * currentAD) * physicalMod","(90 + 1.4 * currentAD) * physicalMod","(135 + 1.4 * currentAD) * physicalMod","(180 + 1.4 * currentAD) * physicalMod","(225 + 1.4 * currentAD) * physicalMod"],"max":[]},"W":{"type":"physical","area":false,"min":["(45 + currentAD) * physicalMod","(75 + currentAD) * physicalMod","(105 + currentAD) * physicalMod","(135 + currentAD) * physicalMod","(165 + currentAD) * physicalMod"],"max":[]},"E":{"type":"physical","area":false,"min":["(80 + 0.06 * maxHP) * physicalMod","(115 + 0.06 * maxHP) * physicalMod","(150 + 0.06 * maxHP) * physicalMod","(185 + 0.06 * maxHP) * physicalMod","(220 + 0.06 * maxHP) * physicalMod"],"max":[]},"R":{"type":"physical","area":true,"min":["(200 + 0.5 * bonusAD + currentAP) * physicalMod","(300 + 0.5 * bonusAD + currentAP) * physicalMod","(400 + 0.5 * bonusAD + currentAP) * physicalMod"],"max":["(300 + 1.5 * currentAP + 0.75 * bonusAD) * physicalMod","(450 + 1.5 * currentAP + 0.75 * bonusAD) * physicalMod","(600 + 1.5 * currentAP + 0.75 * bonusAD) * physicalMod"]}}